mpl2nc
