Metadata-Version: 2.1
Name: mpl2nc
Version: 1.4.1
Summary: Convert Sigma Space Micro Pulse Lidar (MPL) data files to NetCDF
Home-page: https://github.com/peterkuma/mpl2nc
Author: Peter Kuma
Author-email: peter@peterkuma.net
License: MIT
Keywords: sigmaspace,mpl,lidar,netcdf
Classifier: Development Status :: 5 - Production/Stable
Classifier: Environment :: Console
Classifier: Intended Audience :: Science/Research
Classifier: License :: OSI Approved :: MIT License
Classifier: Operating System :: OS Independent
Classifier: Programming Language :: Python :: 3
Classifier: Topic :: Scientific/Engineering :: Atmospheric Science
License-File: LICENSE.md
